<annotation>
	<folder>第一輪</folder>
	<filename>WIN_20200528_19_55_15_Pro.jpg</filename>
	<path>D:\Users\User\Desktop\0528補拍\第一輪\WIN_20200528_19_55_15_Pro.jpg</path>
	<source>
		<database>Unknown</database>
	</source>
	<size>
		<width>1280</width>
		<height>720</height>
		<depth>3</depth>
	</size>
	<segmented>0</segmented>
	<object>
		<name>hamburger</name>
		<pose>Unspecified</pose>
		<truncated>0</truncated>
		<difficult>0</difficult>
		<bndbox>
			<xmin>335</xmin>
			<ymin>65</ymin>
			<xmax>612</xmax>
			<ymax>352</ymax>
		</bndbox>
	</object>
</annotation>
